pyproject.toml
setup.py
skplan/__init__.py
skplan/collision.py
skplan/kinematics.py
skplan/py.typed
skplan/sdf.py
skplan/space.py
skplan/trajectory.py
skplan.egg-info/PKG-INFO
skplan.egg-info/SOURCES.txt
skplan.egg-info/dependency_links.txt
skplan.egg-info/requires.txt
skplan.egg-info/top_level.txt
skplan/robot/__init__.py
skplan/robot/pr2.py
skplan/solver/__init__.py
skplan/solver/optimization.py
skplan/solver/rrt.py
skplan/utils/__init__.py
skplan/utils/urdf.py
skplan/viewer/__init__.py
skplan/viewer/skrobot_viewer.py